pysolar/__init__.py
pysolar/__init__.pyi
pysolar/constants.py
pysolar/constants.pyi
pysolar/elevation.py
pysolar/elevation.pyi
pysolar/numeric.py
pysolar/radiation.py
pysolar/radiation.pyi
pysolar/rest.py
pysolar/simulate.py
pysolar/simulate.pyi
pysolar/solar.py
pysolar/solar.pyi
pysolar/solartime.py
pysolar/solartime.pyi
pysolar/tzinfo_check.py
pysolar/util.py
pysolar/util.pyi
pysolar-0.12.dist-info/COPYING
pysolar-0.12.dist-info/METADATA
pysolar-0.12.dist-info/WHEEL
pysolar-0.12.dist-info/top_level.txt
pysolar-0.12.dist-info/RECORD
